tbk
