Metadata-Version: 1.1
Name: tbk
Version: 0.1.1
Summary: Python implementation of Transbank's Webpay protocol.
Home-page: http://github.com/pedroburon/tbk
Author: Pedro Buron
Author-email: pedroburonv@gmail.com
License: GPLv2
Keywords: webpay,chile,payments,transbank
Platform: UNKNOWN
Classifier: Development Status :: 4 - Beta
Classifier: Intended Audience :: Developers
Classifier: Programming Language :: Python
Classifier: Topic :: Software Development :: Libraries :: Python Modules
Classifier: Programming Language :: Python :: 2.7
Classifier: Environment :: Console
Classifier: Environment :: Web Environment
Classifier: License :: OSI Approved :: GNU General Public License v2 (GPLv2)
